<?xml version="1.0" encoding="UTF-8"?>
<!-- Generator: reqtify -->

<Root>
	<ELEMENT type="" label="Modeling/Rhapsody/ComponentsCreation/ComponentsCreation" uri="orchestra://Rhapsody/Modeling%2FRhapsody%2FComponentsCreation%2FComponentsCreation">
		<PROPERTIES>
			<PROPERTY name="toolid" type="string" nature="PapeeteDocInternal" />
		</PROPERTIES>
		<ELEMENT type="Package" label="(Modeling/Rhapsody/ComponentsCreation/ComponentsCreation Package) Default" fullName="Default" uri="orchestra://Rhapsody/Modeling%2FRhapsody%2FComponentsCreation%2FComponentsCreation/Package/GUID%2018e11ee6%2D67da%2D4afe%2D8619%2Df4b3325cd97b">
			<PROPERTIES>
				<PROPERTY name="toolid" type="string" nature="PapeeteDocInternal">GUID 18e11ee6-67da-4afe-8619-f4b3325cd97b</PROPERTY>
			</PROPERTIES>
		</ELEMENT>
		<ELEMENT type="Profile" label="(Modeling/Rhapsody/ComponentsCreation/ComponentsCreation Profile) SoftwareArchitectCpp" fullName="SoftwareArchitectCpp" uri="orchestra://Rhapsody/Modeling%2FRhapsody%2FComponentsCreation%2FComponentsCreation/Profile/GUID%20c4330c76%2D1cd6%2D4dbd%2Dbdff%2D600355b9f34d">
			<PROPERTIES>
				<PROPERTY name="toolid" type="string" nature="PapeeteDocInternal">GUID c4330c76-1cd6-4dbd-bdff-600355b9f34d</PROPERTY>
			</PROPERTIES>
		</ELEMENT>
		<ELEMENT type="Profile" label="(Modeling/Rhapsody/ComponentsCreation/ComponentsCreation Profile) CodeCentricCpp" fullName="CodeCentricCpp" uri="orchestra://Rhapsody/Modeling%2FRhapsody%2FComponentsCreation%2FComponentsCreation/Profile/GUID%205bc6cd73%2Dd83c%2D4d02%2Db530%2D2cc953376a5f">
			<PROPERTIES>
				<PROPERTY name="toolid" type="string" nature="PapeeteDocInternal">GUID 5bc6cd73-d83c-4d02-b530-2cc953376a5f</PROPERTY>
			</PROPERTIES>
			<LINKS_TO_ELEMENTS>
				<ELEMENT_REFERENCE uri="orchestra://Rhapsody/Modeling%2FRhapsody%2FComponentsCreation%2FComponentsCreation/Stereotype/GUID%20c4916b7f%2D5ca2%2D41a3%2Db8a9%2D6ac22b145b51" fullName="Settings" label="Settings" linkType="stereotype" linkDirection="out" />
			</LINKS_TO_ELEMENTS>
			<ELEMENT type="Stereotype" label="(Modeling/Rhapsody/ComponentsCreation/ComponentsCreation Stereotype) Regenerate" fullName="CodeCentricCpp.Regenerate" uri="orchestra://Rhapsody/Modeling%2FRhapsody%2FComponentsCreation%2FComponentsCreation/Stereotype/GUID%2000b2f94f%2D077b%2D450a%2D8fa9%2D83e253a25f82">
				<PROPERTIES>
					<PROPERTY name="toolid" type="string" nature="PapeeteDocInternal">GUID 00b2f94f-077b-450a-8fa9-83e253a25f82</PROPERTY>
				</PROPERTIES>
			</ELEMENT>
		</ELEMENT>
		<ELEMENT type="Package" label="(Modeling/Rhapsody/ComponentsCreation/ComponentsCreation Package) package_0" fullName="package_0" uri="orchestra://Rhapsody/Modeling%2FRhapsody%2FComponentsCreation%2FComponentsCreation/Package/GUID%20c12c7641%2Dbdfb%2D4ca1%2D8a34%2D08428828610f">
			<PROPERTIES>
				<PROPERTY name="toolid" type="string" nature="PapeeteDocInternal">GUID c12c7641-bdfb-4ca1-8a34-08428828610f</PROPERTY>
			</PROPERTIES>
			<LINKS_TO_ELEMENTS>
				<ELEMENT_REFERENCE uri="orchestra://Rhapsody/Modeling%2FRhapsody%2FComponentsCreation%2FComponentsCreation/ObjectModelDiagram/GUID%208d3d8509%2Da270%2D47e1%2D8494%2D08094f621851" fullName="Model1" label="Model1" linkType="mainDiagram" linkDirection="out" />
			</LINKS_TO_ELEMENTS>
			<ELEMENT type="ComponentDiagram" label="(Modeling/Rhapsody/ComponentsCreation/ComponentsCreation ComponentDiagram) Components" fullName="package_0.Components" uri="orchestra://Rhapsody/Modeling%2FRhapsody%2FComponentsCreation%2FComponentsCreation/ComponentDiagram/GUID%2040e3789b%2D0ff4%2D42b9%2Da3be%2D0e22ff4ac2af">
				<PROPERTIES>
					<PROPERTY name="toolid" type="string" nature="PapeeteDocInternal">GUID 40e3789b-0ff4-42b9-a3be-0e22ff4ac2af</PROPERTY>
				</PROPERTIES>
				<LINKS_TO_ELEMENTS>
					<ELEMENT_REFERENCE uri="orchestra://Rhapsody/Modeling%2FRhapsody%2FComponentsCreation%2FComponentsCreation/Package/GUID%20c12c7641%2Dbdfb%2D4ca1%2D8a34%2D08428828610f" fullName="package_0" label="package_0" linkType="Reference" linkDirection="out" />
					<ELEMENT_REFERENCE uri="orchestra://Rhapsody/Modeling%2FRhapsody%2FComponentsCreation%2FComponentsCreation/Requirement/GUID%203c97068a%2Daac1%2D4317%2Dbed9%2Df484b57d9889" fullName="package_0.requirement_1" label="requirement_1" linkType="Reference" linkDirection="out" />
					<ELEMENT_REFERENCE uri="orchestra://Rhapsody/Modeling%2FRhapsody%2FComponentsCreation%2FComponentsCreation/Requirement/GUID%20991313fe%2D79ae%2D4244%2Da1ef%2D5dd7ad4be6de" fullName="package_0.requirement_2" label="requirement_2" linkType="Reference" linkDirection="out" />
					<ELEMENT_REFERENCE uri="orchestra://Rhapsody/Modeling%2FRhapsody%2FComponentsCreation%2FComponentsCreation/Requirement/GUID%2067a9d1f2%2De497%2D4c0a%2Da3a1%2D523eb3477ed1" fullName="package_0.requirement_3" label="requirement_3" linkType="Reference" linkDirection="out" />
				</LINKS_TO_ELEMENTS>
			</ELEMENT>
			<ELEMENT type="Requirement" label="(Modeling/Rhapsody/ComponentsCreation/ComponentsCreation Requirement) requirement_1" fullName="package_0.requirement_1" uri="orchestra://Rhapsody/Modeling%2FRhapsody%2FComponentsCreation%2FComponentsCreation/Requirement/GUID%203c97068a%2Daac1%2D4317%2Dbed9%2Df484b57d9889">
				<PROPERTIES>
					<PROPERTY name="toolid" type="string" nature="PapeeteDocInternal">GUID 3c97068a-aac1-4317-bed9-f484b57d9889</PROPERTY>
				</PROPERTIES>
			</ELEMENT>
			<ELEMENT type="Requirement" label="(Modeling/Rhapsody/ComponentsCreation/ComponentsCreation Requirement) requirement_2" fullName="package_0.requirement_2" uri="orchestra://Rhapsody/Modeling%2FRhapsody%2FComponentsCreation%2FComponentsCreation/Requirement/GUID%20991313fe%2D79ae%2D4244%2Da1ef%2D5dd7ad4be6de">
				<PROPERTIES>
					<PROPERTY name="toolid" type="string" nature="PapeeteDocInternal">GUID 991313fe-79ae-4244-a1ef-5dd7ad4be6de</PROPERTY>
				</PROPERTIES>
			</ELEMENT>
			<ELEMENT type="Requirement" label="(Modeling/Rhapsody/ComponentsCreation/ComponentsCreation Requirement) requirement_3" fullName="package_0.requirement_3" uri="orchestra://Rhapsody/Modeling%2FRhapsody%2FComponentsCreation%2FComponentsCreation/Requirement/GUID%2067a9d1f2%2De497%2D4c0a%2Da3a1%2D523eb3477ed1">
				<PROPERTIES>
					<PROPERTY name="toolid" type="string" nature="PapeeteDocInternal">GUID 67a9d1f2-e497-4c0a-a3a1-523eb3477ed1</PROPERTY>
				</PROPERTIES>
			</ELEMENT>
		</ELEMENT>
		<ELEMENT type="Profile" label="(Modeling/Rhapsody/ComponentsCreation/ComponentsCreation Profile) CGCompatibilityPre761Cpp" fullName="CGCompatibilityPre761Cpp" uri="orchestra://Rhapsody/Modeling%2FRhapsody%2FComponentsCreation%2FComponentsCreation/Profile/GUID%200838347a%2Dc933%2D40e3%2D9d7e%2D812acdb081ee">
			<PROPERTIES>
				<PROPERTY name="toolid" type="string" nature="PapeeteDocInternal">GUID 0838347a-c933-40e3-9d7e-812acdb081ee</PROPERTY>
			</PROPERTIES>
			<LINKS_TO_ELEMENTS>
				<ELEMENT_REFERENCE uri="orchestra://Rhapsody/Modeling%2FRhapsody%2FComponentsCreation%2FComponentsCreation/Stereotype/GUID%20c4916b7f%2D5ca2%2D41a3%2Db8a9%2D6ac22b145b51" fullName="Settings" label="Settings" linkType="stereotype" linkDirection="out" />
			</LINKS_TO_ELEMENTS>
		</ELEMENT>
		<ELEMENT type="Profile" label="(Modeling/Rhapsody/ComponentsCreation/ComponentsCreation Profile) CGCompatibilityPre80Cpp" fullName="CGCompatibilityPre80Cpp" uri="orchestra://Rhapsody/Modeling%2FRhapsody%2FComponentsCreation%2FComponentsCreation/Profile/GUID%20cdc61ea8%2D5d48%2D43f9%2D9f97%2Daf672c36c918">
			<PROPERTIES>
				<PROPERTY name="toolid" type="string" nature="PapeeteDocInternal">GUID cdc61ea8-5d48-43f9-9f97-af672c36c918</PROPERTY>
			</PROPERTIES>
			<LINKS_TO_ELEMENTS>
				<ELEMENT_REFERENCE uri="orchestra://Rhapsody/Modeling%2FRhapsody%2FComponentsCreation%2FComponentsCreation/Stereotype/GUID%20c4916b7f%2D5ca2%2D41a3%2Db8a9%2D6ac22b145b51" fullName="Settings" label="Settings" linkType="stereotype" linkDirection="out" />
			</LINKS_TO_ELEMENTS>
		</ELEMENT>
		<ELEMENT type="Profile" label="(Modeling/Rhapsody/ComponentsCreation/ComponentsCreation Profile) CGCompatibilityPre803Cpp" fullName="CGCompatibilityPre803Cpp" uri="orchestra://Rhapsody/Modeling%2FRhapsody%2FComponentsCreation%2FComponentsCreation/Profile/GUID%202c6673a1%2D7843%2D43a4%2D92d5%2D93795ef7e229">
			<PROPERTIES>
				<PROPERTY name="toolid" type="string" nature="PapeeteDocInternal">GUID 2c6673a1-7843-43a4-92d5-93795ef7e229</PROPERTY>
			</PROPERTIES>
			<LINKS_TO_ELEMENTS>
				<ELEMENT_REFERENCE uri="orchestra://Rhapsody/Modeling%2FRhapsody%2FComponentsCreation%2FComponentsCreation/Stereotype/GUID%20c4916b7f%2D5ca2%2D41a3%2Db8a9%2D6ac22b145b51" fullName="Settings" label="Settings" linkType="stereotype" linkDirection="out" />
			</LINKS_TO_ELEMENTS>
		</ELEMENT>
		<ELEMENT type="ObjectModelDiagram" label="(Modeling/Rhapsody/ComponentsCreation/ComponentsCreation ObjectModelDiagram) Model1" fullName="Model1" uri="orchestra://Rhapsody/Modeling%2FRhapsody%2FComponentsCreation%2FComponentsCreation/ObjectModelDiagram/GUID%208d3d8509%2Da270%2D47e1%2D8494%2D08094f621851">
			<PROPERTIES>
				<PROPERTY name="toolid" type="string" nature="PapeeteDocInternal">GUID 8d3d8509-a270-47e1-8494-08094f621851</PROPERTY>
			</PROPERTIES>
		</ELEMENT>
		<ELEMENT type="Component" label="(Modeling/Rhapsody/ComponentsCreation/ComponentsCreation Component) DefaultComponent" fullName="DefaultComponent" uri="orchestra://Rhapsody/Modeling%2FRhapsody%2FComponentsCreation%2FComponentsCreation/Component/GUID%20699aa6ca%2Df798%2D4841%2D9cd0%2Dbf5f52901362">
			<PROPERTIES>
				<PROPERTY name="toolid" type="string" nature="PapeeteDocInternal">GUID 699aa6ca-f798-4841-9cd0-bf5f52901362</PROPERTY>
			</PROPERTIES>
			<ELEMENT type="HyperLink" label="(Modeling/Rhapsody/ComponentsCreation/ComponentsCreation HyperLink) Edit Makefile" fullName="DefaultComponent.DefaultConfig.Edit+Makefile" uri="orchestra://Rhapsody/Modeling%2FRhapsody%2FComponentsCreation%2FComponentsCreation/HyperLink/GUID%20812a06eb%2D6e31%2D48e9%2D8202%2D99d987b2c60a">
				<PROPERTIES>
					<PROPERTY name="toolid" type="string" nature="PapeeteDocInternal">GUID 812a06eb-6e31-48e9-8202-99d987b2c60a</PROPERTY>
				</PROPERTIES>
			</ELEMENT>
			<ELEMENT type="HyperLink" label="(Modeling/Rhapsody/ComponentsCreation/ComponentsCreation HyperLink) Edit Main File" fullName="DefaultComponent.DefaultConfig.Edit+Main+File" uri="orchestra://Rhapsody/Modeling%2FRhapsody%2FComponentsCreation%2FComponentsCreation/HyperLink/GUID%20c63e559c%2Dfeb0%2D4696%2D825c%2Dde771f1ad269">
				<PROPERTIES>
					<PROPERTY name="toolid" type="string" nature="PapeeteDocInternal">GUID c63e559c-feb0-4696-825c-de771f1ad269</PROPERTY>
				</PROPERTIES>
			</ELEMENT>
		</ELEMENT>
		<ELEMENT type="Dependency" label="(Modeling/Rhapsody/ComponentsCreation/ComponentsCreation Dependency) CodeCentricCpp" fullName="CodeCentricCpp" uri="orchestra://Rhapsody/Modeling%2FRhapsody%2FComponentsCreation%2FComponentsCreation/Dependency/GUID%203fdfd62e%2D1a67%2D4950%2D9dc3%2D6d6c17bd4263">
			<PROPERTIES>
				<PROPERTY name="toolid" type="string" nature="PapeeteDocInternal">GUID 3fdfd62e-1a67-4950-9dc3-6d6c17bd4263</PROPERTY>
			</PROPERTIES>
			<LINKS_TO_ELEMENTS>
				<ELEMENT_REFERENCE uri="orchestra://Rhapsody/Modeling%2FRhapsody%2FComponentsCreation%2FComponentsCreation/Stereotype/GUID%20d2eca2c1%2De5a5%2D4296%2D9453%2D29283c4ed8bc" fullName="AppliedProfile" label="AppliedProfile" linkType="stereotype" linkDirection="out" />
				<ELEMENT_REFERENCE uri="orchestra://Rhapsody/Modeling%2FRhapsody%2FComponentsCreation%2FComponentsCreation/Profile/GUID%205bc6cd73%2Dd83c%2D4d02%2Db530%2D2cc953376a5f" fullName="CodeCentricCpp" label="CodeCentricCpp" linkType="Dependency" linkDirection="out" />
			</LINKS_TO_ELEMENTS>
		</ELEMENT>
	</ELEMENT>
</Root>